tts_webui_extension/songbloom/__init__.py
tts_webui_extension/songbloom/disable_flash_attention.py
tts_webui_extension/songbloom/gradio_ui.py
tts_webui_extension/songbloom/main.py
tts_webui_extension_songbloom-0.1.2.dist-info/licenses/LICENSE
tts_webui_extension_songbloom-0.1.2.dist-info/METADATA
tts_webui_extension_songbloom-0.1.2.dist-info/WHEEL
tts_webui_extension_songbloom-0.1.2.dist-info/top_level.txt
tts_webui_extension_songbloom-0.1.2.dist-info/RECORD
